explore.py
object_explore-0.1.11.dist-info/LICENSE
object_explore-0.1.11.dist-info/METADATA
object_explore-0.1.11.dist-info/WHEEL
object_explore-0.1.11.dist-info/top_level.txt
object_explore-0.1.11.dist-info/RECORD
